safe_parse/__init__.py
safe_parse/safe_parse.py
safe_parse-1.0.0.dist-info/licenses/LICENSE
safe_parse-1.0.0.dist-info/METADATA
safe_parse-1.0.0.dist-info/WHEEL
safe_parse-1.0.0.dist-info/top_level.txt
safe_parse-1.0.0.dist-info/RECORD
