Metadata-Version: 2.4
Name: safe-parse
Version: 1.0.0
Summary: Dot notation access for dict/JSON with safety fallback.
Author: Nandkishor Kumawat
License: MIT License
Project-URL: Homepage, https://github.com/nandkishor-kumawat/safe-parse
Project-URL: Issues, https://github.com/nandkishor-kumawat/safe-parse/issues
Classifier: Programming Language :: Python :: 3
Classifier: License :: OSI Approved :: MIT License
Classifier: Operating System :: OS Independent
Requires-Python: >=3.6
License-File: LICENSE
Dynamic: license-file
